tf_img_mod/__init__.py
mk_tf_img_mod-0.0.0.3.dist-info/LICENSE
mk_tf_img_mod-0.0.0.3.dist-info/METADATA
mk_tf_img_mod-0.0.0.3.dist-info/WHEEL
mk_tf_img_mod-0.0.0.3.dist-info/top_level.txt
mk_tf_img_mod-0.0.0.3.dist-info/RECORD
