Metadata-Version: 2.1
Name: mk-tf-img-mod
Version: 0.0.0.3
Summary: Easy to use Image Learning Module for Tensorflow
Home-page: https://mknxgn.com/
Author: Mark Cartagena
Author-email: mark@mknxgn.com
License: UNKNOWN
Platform: UNKNOWN
Classifier: Programming Language :: Python :: 3
Classifier: License :: OSI Approved :: MIT License
Classifier: Operating System :: OS Independent
Requires-Dist: tensorflow
Requires-Dist: mknxgn-essentials
Requires-Dist: requests
